{"cameraMode":{"drawMode":0,"name":"Shaded","section":"Shading Mode"},"sceneLighting":false,"audioPlay":false,"sceneViewState":{"m_AlwaysRefresh":false,"showFog":true,"showSkybox":false,"showFlares":true,"showImageEffects":true,"showParticleSystems":true,"showVisualEffectGraphs":true,"m_FxEnabled":true},"in2DMode":false,"pivot":{"x":12.810614585876465,"y":0.9848790168762207,"z":-1.8519524335861207},"rotation":{"x":0.1278328150510788,"y":-0.7604129314422607,"z":0.15755632519721986,"w":0.6169395446777344},"size":6.054272651672363,"orthographic":false}